<?xml version="1.0" encoding="UTF-8"?>
<configuration>
  <property>
    <name>yarn.nodemanager.address</name>
    <value>0.0.0.0:8039</value>
  </property>
  <property>
    <name>yarn.resourcemanager.hostname</name>
    <value>$HDFS_MASTER</value>
    <description>Yarn Config</description>
  </property>
  <property>
    <name>yarn.nodemanager.aux-services</name>
    <value>mapreduce_shuffle</value>
  </property>
  <property>
    <name>yarn.nodemanager.aux-services.mapreduce_shuffle.class</name>
    <value>org.apache.hadoop.mapred.ShuffleHandler</value>
  </property>
  <property>
    <name>yarn.resourcemanager.resource-tracker.address</name>
    <value>$HDFS_MASTER:8025</value>
  </property>
  <property>
    <name>yarn.resourcemanager.scheduler.address</name>
    <value>$HDFS_MASTER:8030</value>
  </property>
  <property>
    <name>yarn.app.mapreduce.am.job.client.port-range</name>
    <value>56000-56020</value>
  </property>
</configuration>
